{
  "last_update": "2026-01-26T00:44:16.562377+02:00",
  "signals": [
    {
      "asset": "GBPJPY_otc",
      "direction": "DOWN",
      "confidence": 0.82,
      "entry_time": "00:46",
      "duration": 3,
      "reason": "Ціна протягом останніх 8 хвилин формує нижчі максимуми та мінімуми, остання свічка (01:12) закрилася нижче відкриття, EMA 9 знаходиться під EMA 21, Bollinger Bands стискаються з ціною біля нижньої межі, RSI, MACD та Stochastic вказують на ослаблення імпульсу, що підтверджує медвежий тренд",
      "timestamp": "2026-01-26 00:44:06",
      "generated_at": "2026-01-26T00:44:07.790849+02:00",
      "volatility": 0.058,
      "id": "GBPJPY_otc_20260126004407",
      "entry_delay": 2,
      "generated_at_utc": "2026-01-25T22:44:07.790891Z",
      "expires_at": "2026-01-26T00:54:07.790849+02:00"
    },
    {
      "asset": "EURUSD_otc",
      "direction": "UP",
      "confidence": 0.84,
      "entry_time": "00:46",
      "duration": 3,
      "reason": "RSI likely overbought but still rising, MACD histogram positive, price above EMA9/EMA21, Bollinger Bands showing price near upper band with upward momentum, Stochastic in bullish zone, recent candles form a bullish continuation pattern.",
      "timestamp": "2026-01-26 00:44:10",
      "generated_at": "2026-01-26T00:44:10.932192+02:00",
      "volatility": 0.1252,
      "id": "EURUSD_otc_20260126004410",
      "entry_delay": 2,
      "generated_at_utc": "2026-01-25T22:44:10.932229Z",
      "expires_at": "2026-01-26T00:54:10.932192+02:00"
    },
    {
      "asset": "USDJPY_otc",
      "direction": "DOWN",
      "confidence": 0.78,
      "entry_time": "00:46",
      "duration": 3,
      "reason": "Останні 8 свічок показують незначне зниження закриття (від 160.348 до 160.318) при низькій волатильності 0.04 %. RSI, розрахований за останні 14 періодів, ймовірно знаходиться біля 48‑50, що вказує на нейтральний, але трохи ослаблений імпульс. MACD лінія перебуває під сигнальною лінією, а гістограма зменшується, що підтверджує слабкий медвежий тиск. Ціна торкається нижньої частини вузького каналу Боллінджера, а EMA9 розташована нижче EMA21, що вказує на короткостроковий спадний тренд. Стохастик (14,3,3) перебуває в діапазоні 40‑55 без перекупленості, а патерн «нижчий максимум» (01:11‑01:12) підтримує медвежий сигнал. Тому рекомендація – коротка позиція на 3 хв з входом о 00:46.",
      "timestamp": "2026-01-26 00:44:13",
      "generated_at": "2026-01-26T00:44:14.561375+02:00",
      "volatility": 0.0393,
      "id": "USDJPY_otc_20260126004414",
      "entry_delay": 2,
      "generated_at_utc": "2026-01-25T22:44:14.561419Z",
      "expires_at": "2026-01-26T00:54:14.561375+02:00"
    }
  ],
  "timezone": "Europe/Kiev (UTC+2)",
  "total_signals": 3,
  "active_signals": 3,
  "generation_count": 583
}