{
  "last_update": "2026-01-13T15:39:14.551612+02:00",
  "signals": [
    {
      "asset": "GBPJPY_otc",
      "direction": "DOWN",
      "confidence": 0.75,
      "entry_time": "15:41",
      "duration": 3,
      "reason": "Тренд вниз. Волатильність: 0.38%",
      "timestamp": "2026-01-13 15:39:02",
      "generated_at": "2026-01-13T15:39:04.665009+02:00",
      "volatility": 0.3811,
      "id": "GBPJPY_otc_20260113153904",
      "entry_delay": 2,
      "generated_at_utc": "2026-01-13T13:39:04.665044Z",
      "expires_at": "2026-01-13T15:49:04.665009+02:00"
    },
    {
      "asset": "EURUSD_otc",
      "direction": "DOWN",
      "confidence": 0.75,
      "entry_time": "15:41",
      "duration": 3,
      "reason": "Тренд вниз. Волатильність: 0.08%",
      "timestamp": "2026-01-13 15:39:07",
      "generated_at": "2026-01-13T15:39:08.839888+02:00",
      "volatility": 0.0761,
      "id": "EURUSD_otc_20260113153908",
      "entry_delay": 2,
      "generated_at_utc": "2026-01-13T13:39:08.839929Z",
      "expires_at": "2026-01-13T15:49:08.839888+02:00"
    },
    {
      "asset": "USDJPY_otc",
      "direction": "DOWN",
      "confidence": 0.86,
      "entry_time": "15:41",
      "duration": 3,
      "reason": "Price has been declining over the last 8 minutes, EMA9 is below EMA21, MACD histogram turned negative, RSI is around 45 and trending down, Bollinger Bands are narrowing with price near the lower band, Stochastic is below 50, and a bearish engulfing pattern appeared at 16:01‑16:02. All signals point to a short‑term down move.",
      "timestamp": "2026-01-13 15:39:11",
      "generated_at": "2026-01-13T15:39:12.550782+02:00",
      "volatility": 0.1034,
      "id": "USDJPY_otc_20260113153912",
      "entry_delay": 2,
      "generated_at_utc": "2026-01-13T13:39:12.550813Z",
      "expires_at": "2026-01-13T15:49:12.550782+02:00"
    }
  ],
  "timezone": "Europe/Kiev (UTC+2)",
  "total_signals": 3,
  "active_signals": 3,
  "generation_count": 384
}