{
  "last_update": "2025-12-29T13:41:20.459440+02:00",
  "signals": [
    {
      "asset": "GBPJPY_otc",
      "direction": "UP",
      "confidence": 0.85,
      "entry_time": "13:43",
      "duration": 2,
      "reason": "Загальний тренд вгору, рівень підтримки на 237.40, RSI на рівні 60, MACD показує позитивну тенденцію",
      "timestamp": "2025-12-29 13:41:18",
      "generated_at": "2025-12-29T13:41:18.914023+02:00",
      "id": "GBPJPY_otc_20251229134118"
    },
    {
      "asset": "EURUSD_otc",
      "direction": "UP",
      "confidence": 0.85,
      "entry_time": "13:43",
      "duration": 2,
      "reason": "Загальний тренд вгору, рівень підтримки на 1.1659, RSI показує незначне перевищення, що свідчить про можливе подальше зростання.",
      "timestamp": "2025-12-29 13:41:19",
      "generated_at": "2025-12-29T13:41:19.523893+02:00",
      "id": "EURUSD_otc_20251229134119"
    },
    {
      "asset": "USDJPY_otc",
      "direction": "DOWN",
      "confidence": 0.85,
      "entry_time": "13:43",
      "duration": 2,
      "reason": "Відповідно до аналізу останніх 10 свічок, спостерігається загальний тренд вниз. Рівень опору знаходиться біля 154.55, а рівень підтримки - біля 154.38. Індикатор RSI показує перевищення, що свідчить про можливе подальше зниження ціни. Волатильність відносно низька, що дозволяє очікувати більш передбачуваного руху. Японські свічкові патерни також вказують на можливе зниження.",
      "timestamp": "2025-12-29 13:41:19",
      "generated_at": "2025-12-29T13:41:20.459149+02:00",
      "id": "USDJPY_otc_20251229134120"
    }
  ],
  "timezone": "Europe/Kiev (UTC+2)",
  "total_signals": 3,
  "active_signals": 0
}