{
  "last_update": "2026-01-05T13:57:01.847823+02:00",
  "signals": [
    {
      "asset": "GBPJPY_otc",
      "direction": "DOWN",
      "confidence": 0.78,
      "entry_time": "13:57",
      "duration": 3,
      "reason": "Ціна нижча за SMA5 (205.745) і SMA10 (205.861), тренд DOWN, волатильність 0.298% – середня, тому очікуємо подальше падіння протягом 3‑4 хвилин.",
      "timestamp": "2026-01-05 13:56:51",
      "generated_at": "2026-01-05T13:56:53.010009+02:00",
      "volatility": 0.2983,
      "id": "GBPJPY_otc_20260105135653",
      "entry_delay": 1,
      "generated_at_utc": "2026-01-05T11:56:53.010057Z",
      "expires_at": "2026-01-05T14:06:53.010009+02:00"
    },
    {
      "asset": "EURUSD_otc",
      "direction": "DOWN",
      "confidence": 0.78,
      "entry_time": "13:58",
      "duration": 5,
      "reason": "Тренд вниз, ціна нижче SMA10, волатильність низька (<0.2%), останні свічки показують слабке підвищення, але загальна динаміка зниження, підтримка SMA5.",
      "timestamp": "2026-01-05 13:56:55",
      "generated_at": "2026-01-05T13:56:56.751545+02:00",
      "volatility": 0.1873,
      "id": "EURUSD_otc_20260105135656",
      "entry_delay": 2,
      "generated_at_utc": "2026-01-05T11:56:56.751593Z",
      "expires_at": "2026-01-05T14:06:56.751545+02:00"
    },
    {
      "asset": "USDJPY_otc",
      "direction": "UP",
      "confidence": 0.82,
      "entry_time": "13:58",
      "duration": 5,
      "reason": "Ціна знаходиться вище SMA5 і SMA10, тренд визначений як UP, волатильність низька (<0.2%), тому очікуємо стабільний рух вгору протягом 5 хвилин.",
      "timestamp": "2026-01-05 13:56:59",
      "generated_at": "2026-01-05T13:56:59.846360+02:00",
      "volatility": 0.0491,
      "id": "USDJPY_otc_20260105135659",
      "entry_delay": 2,
      "generated_at_utc": "2026-01-05T11:56:59.846407Z",
      "expires_at": "2026-01-05T14:06:59.846360+02:00"
    }
  ],
  "timezone": "Europe/Kyiv (UTC+2)",
  "total_signals": 3,
  "active_signals": 3,
  "generation_count": 39
}