{
  "last_update": "2025-12-29T22:16:32.637140+02:00",
  "signals": [
    {
      "asset": "GBPJPY_otc",
      "direction": "DOWN",
      "confidence": 0.73,
      "entry_time": "22:18",
      "duration": 5,
      "reason": "Низька волатильність (<0.2%), остання 2‑хв свічка закрилася на мінімумі (Low=240.232) після зниження ціни, тиск вниз переважає, підтримка ближче до 240.15‑240.20, опір вище 240.45, що вказує на короткостроковий спад.",
      "timestamp": "2025-12-29 22:16:17",
      "generated_at": "2025-12-29T22:16:19.536951+02:00",
      "volatility": 0.10346514481818189,
      "entry_time_utc": "2025-12-29T20:18:00+00:00",
      "entry_time_kyiv": "22:18",
      "id": "GBPJPY_otc_20251229221619"
    }
  ],
  "timezone": "Europe/Kiev (UTC+2)",
  "total_signals": 1,
  "active_signals": 0
}